.gitignore
CHANGES.txt
DESCRIPTION.md
LICENSE
MANIFEST
MANIFEST.in
README.md
setup.py
C:/Users/James/Lumate/AdTrade/Python-Data-Writers/.gitignore
C:/Users/James/Lumate/AdTrade/Python-Data-Writers/CHANGES.txt
C:/Users/James/Lumate/AdTrade/Python-Data-Writers/DESCRIPTION.md
C:/Users/James/Lumate/AdTrade/Python-Data-Writers/LICENSE
C:/Users/James/Lumate/AdTrade/Python-Data-Writers/MANIFEST
C:/Users/James/Lumate/AdTrade/Python-Data-Writers/MANIFEST.in
C:/Users/James/Lumate/AdTrade/Python-Data-Writers/README.md
C:/Users/James/Lumate/AdTrade/Python-Data-Writers/setup.py
C:/Users/James/Lumate/AdTrade/Python-Data-Writers/datawriters/__init__.py
C:/Users/James/Lumate/AdTrade/Python-Data-Writers/datawriters/aerospikewriter.py
C:/Users/James/Lumate/AdTrade/Python-Data-Writers/datawriters/csvwriter.py
C:/Users/James/Lumate/AdTrade/Python-Data-Writers/datawriters/datawriter.py
C:/Users/James/Lumate/AdTrade/Python-Data-Writers/datawriters/mongowriter.py
C:/Users/James/Lumate/AdTrade/Python-Data-Writers/datawriters/mysqlwriter.py
C:/Users/James/Lumate/AdTrade/Python-Data-Writers/datawriters/notimplementedwriter.py
C:/Users/James/Lumate/AdTrade/Python-Data-Writers/datawriters/postgreswriter.py
C:/Users/James/Lumate/AdTrade/Python-Data-Writers/datawriters/rediswriter.py
C:/Users/James/Lumate/AdTrade/Python-Data-Writers/datawriters/sqlitewriter.py
data_writers.egg-info/PKG-INFO
data_writers.egg-info/SOURCES.txt
data_writers.egg-info/dependency_links.txt
data_writers.egg-info/top_level.txt
datawriters/__init__.py
datawriters/aerospikewriter.py
datawriters/csvwriter.py
datawriters/datawriter.py
datawriters/mongowriter.py
datawriters/mysqlwriter.py
datawriters/notimplementedwriter.py
datawriters/postgreswriter.py
datawriters/rediswriter.py
datawriters/sqlitewriter.py