Metadata-Version: 1.1
Name: data-writers
Version: 0.5.3
Summary: Write to multiple databases and formats easily from python
Home-page: https://github.com/jamesmarlowe/Python-Data-Writers
Author: James Marlowe (jamesmarlowe)
Author-email: jameskmarlowe@gmail.com
License: FreeBSD
Keywords: database write csv data postgres mysql redis sqlite mongo aerospike
Platform: UNKNOWN
Classifier: Development Status :: 4 - Beta
Classifier: Intended Audience :: Developers
Classifier: Topic :: Software Development :: Build Tools
Classifier: License :: OSI Approved :: BSD License
Classifier: Programming Language :: Python :: 2
Classifier: Programming Language :: Python :: 2.6
Classifier: Programming Language :: Python :: 2.7
Classifier: Programming Language :: Python :: 3
Classifier: Programming Language :: Python :: 3.2
Classifier: Programming Language :: Python :: 3.3
Classifier: Programming Language :: Python :: 3.4
